README.md
setup.py
Ammonia.egg-info/PKG-INFO
Ammonia.egg-info/SOURCES.txt
Ammonia.egg-info/dependency_links.txt
Ammonia.egg-info/entry_points.txt
Ammonia.egg-info/requires.txt
Ammonia.egg-info/top_level.txt
ammonia/__init__.py
ammonia/app.py
ammonia/config.py
ammonia/exception.py
ammonia/main.py
ammonia/mq.py
ammonia/serializer.py
ammonia/settings.py
ammonia/state.py
ammonia/utils.py
ammonia/backends/__init__.py
ammonia/backends/backend.py
ammonia/backends/models.py
ammonia/base/__init__.py
ammonia/base/loader.py
ammonia/base/registry.py
ammonia/base/result.py
ammonia/base/task.py
ammonia/command/__init__.py
ammonia/command/start.py
ammonia/tests/__init__.py
ammonia/tests/__main__.py
ammonia/tests/test_backends.py
ammonia/tests/test_base.py
ammonia/tests/test_loader.py
ammonia/tests/test_pool.py
ammonia/tests/test_schedule.py
ammonia/tests/test_serializer.py
ammonia/tests/test_task.py
ammonia/worker/__init__.py
ammonia/worker/controller.py
ammonia/worker/listener.py
ammonia/worker/pool.py
ammonia/worker/schedule.py
example/__init__.py
example/ammonia.py
example/tasks.py